django_s3files-0.0.4.2.dist-info/licenses/LICENSE
s3files/__init__.py
s3files/settings.py
s3files/urls.py
s3files/utils.py
s3files/views.py
s3files/templates/s3_files.html
s3files/templatetags/__init__.py
s3files/templatetags/s3files_extras.py
s3files/templatetags/__pycache__/__init__.cpython-313.pyc
s3files/templatetags/__pycache__/s3files_extras.cpython-313.pyc
django_s3files-0.0.4.2.dist-info/METADATA
django_s3files-0.0.4.2.dist-info/WHEEL
django_s3files-0.0.4.2.dist-info/top_level.txt
django_s3files-0.0.4.2.dist-info/RECORD
